auto_build_minecraft/Docker/Dockerfile
auto_build_minecraft/msab.py
auto_build_minecraft/playbook.yml
auto_build_minecraft/tasks/add-hosts.yml
auto_build_minecraft/tasks/create-instance.yml
auto_build_minecraft/tasks/delete-instance.yml
auto_build_minecraft/tasks/download-world-data.yml
auto_build_minecraft/tasks/run-server.yml
auto_build_minecraft/tasks/start-instance.yml
auto_build_minecraft/tasks/stop-instance.yml
auto_build_minecraft-1.0.1.dist-info/LICENSE
auto_build_minecraft-1.0.1.dist-info/METADATA
auto_build_minecraft-1.0.1.dist-info/WHEEL
auto_build_minecraft-1.0.1.dist-info/entry_points.txt
auto_build_minecraft-1.0.1.dist-info/RECORD
